{
  "id": "rss-20260715-006",
  "title": "Optimization Is Not All You Need",
  "source_url": "https://arxiv.org/abs/2607.11977",
  "source_type": "rss",
  "summary": "本文批判性地审视了AI领域的优化文化，认为将语言生成简化为可量化指标的优化过程，虽然提升了流畅度，却丧失了判断文本价值的能力。作者追溯了从预训练、解码、偏好调优到基准测试的整个技术栈，指出优化无法区分错误与创新，却已取代传统机构成为语言合法性的仲裁者。",
  "tags": [
    "AI对齐",
    "优化文化",
    "语言模型",
    "评估基准",
    "技术批判"
  ],
  "status": "draft",
  "created_at": "2026-07-15T18:05:54+08:00",
  "updated_at": "2026-07-15T18:05:54+08:00",
  "metadata": {
    "feed_name": "ArXiv AI"
  },
  "ai_analysis": {
    "relevance_score": 0.9,
    "key_insights": [
      "优化文化将语言价值简化为可量化指标，忽视了判断力。",
      "当前AI系统无法区分文本中的错误与创新。",
      "优化程序已取代传统机构，成为语言合法性的仲裁者。"
    ],
    "category": "AI伦理与批判"
  }
}